pyoma2-0.1.0.dist-info/METADATA
pyoma2-0.1.0.dist-info/WHEEL
pyoma2-0.1.0.dist-info/entry_points.txt
pyoma2-0.1.0.dist-info/licenses/LICENSE
pyoma2/Example_MSpoSER.py
pyoma2/Example_MSpreGER.py
pyoma2/Example_SS.py
pyoma2/OMA.py
pyoma2/__init__.py
pyoma2/algorithm/__init__.py
pyoma2/algorithm/base.py
pyoma2/algorithm/data/__init__.py
pyoma2/algorithm/data/geometry.py
pyoma2/algorithm/data/result.py
pyoma2/algorithm/data/run_params.py
pyoma2/algorithm/fdd.py
pyoma2/algorithm/ssi.py
pyoma2/functions/FDD_funct.py
pyoma2/functions/Gen_funct.py
pyoma2/functions/SSI_funct.py
pyoma2/functions/__init__.py
pyoma2/functions/pLSCF_funct.py
pyoma2/functions/plot_funct.py
pyoma2/logging_handler.py
pyoma2/plot/Sel_from_plot.py
pyoma2/plot/__init__.py
pyoma2/plot/anim_mode.py
pyoma2/test_data/3SL/BG_lines.txt
pyoma2/test_data/3SL/BG_nodes.txt
pyoma2/test_data/3SL/__init__.py
pyoma2/test_data/3SL/geom.xlsx
pyoma2/test_data/3SL/pts_coord.txt
pyoma2/test_data/3SL/sens_coord.txt
pyoma2/test_data/3SL/sens_dir.txt
pyoma2/test_data/3SL/sens_lines.txt
pyoma2/test_data/3SL/sens_map.txt
pyoma2/test_data/3SL/sens_sign.txt
pyoma2/test_data/3SL/set1.npy
pyoma2/test_data/3SL/set2.npy
pyoma2/test_data/3SL/set3.npy
pyoma2/test_data/palisaden/BG_lines.txt
pyoma2/test_data/palisaden/BG_nodes.txt
pyoma2/test_data/palisaden/Palisaden_dataset.npy
pyoma2/test_data/palisaden/__init__.py
pyoma2/test_data/palisaden/geom_pali.xlsx
pyoma2/test_data/palisaden/pts_coord.txt
pyoma2/test_data/palisaden/sens_coord.txt
pyoma2/test_data/palisaden/sens_dir.txt
pyoma2/test_data/palisaden/sens_lines.txt
pyoma2/test_data/palisaden/sens_map.txt
pyoma2/test_data/palisaden/sens_sign.txt
pyoma2/utils/__init__.py
pyoma2/utils/typing.py
pyoma2/utils/utils.py
pyoma2-0.1.0.dist-info/RECORD
