Metadata-Version: 2.1
Name: pyOMA2
Version: 0.1.0
Summary: Software for Structural Health Monitoring with Advanced Signal Processing Techniques
Author-Email: Dag Pasca <dpa@treteknisk.no>, Marco Martino Rosso <marco.rosso@polito.it>, Diego Federico Margoni <diegofederico.margoni@studenti.polito.it>
License: MIT
Requires-Python: <3.12,>=3.8
Requires-Dist: numpy>=1.24.4
Requires-Dist: pandas>=2.0.3
Requires-Dist: scipy>=1.9.3
Requires-Dist: pydantic>=2.5.1
Requires-Dist: tqdm>=4.66.1
Requires-Dist: matplotlib>=3.7.4
